dnreporter/__init__.py
dnreporter/dnreporter.py
dnreporter-0.1.2.dist-info/LICENSE
dnreporter-0.1.2.dist-info/WHEEL
dnreporter-0.1.2.dist-info/METADATA
dnreporter-0.1.2.dist-info/RECORD
